Metadata-Version: 1.1
Name: tapioca-asana
Version: 0.1
Summary: Tapioca Asana: Smart python client for Asana.com API
Home-page: https://github.com/henriquebastos/tapioca-asana
Author: Henrique Bastos
Author-email: henrique@bastos.net
License: MIT
Keywords: asana
Platform: UNKNOWN
Classifier: Development Status :: 5 - Production/Stable
Classifier: Intended Audience :: Developers
Classifier: License :: OSI Approved :: MIT License
Classifier: Natural Language :: English
Classifier: Programming Language :: Python :: 2
Classifier: Programming Language :: Python :: 2.7
Classifier: Programming Language :: Python :: 3
Classifier: Programming Language :: Python :: 3.1
Classifier: Programming Language :: Python :: 3.2
Classifier: Programming Language :: Python :: 3.3
Classifier: Programming Language :: Python :: 3.4
Classifier: Programming Language :: Python :: 3.5
Classifier: Programming Language :: Python :: 3.6
